{
  "race_id": 707,
  "generated_at": "2025-10-21T09:01:54Z",
  "schema": "v3.3",
  "drivers": [
    {
      "driver_id": 707,
      "team": "",
      "best_time_ms": 75480,
      "best_time_raw": "1:15.480",
      "source_session": "Q2",
      "perf_pct": 100.686
    },
    {
      "driver_id": 723,
      "team": "",
      "best_time_ms": 76166,
      "best_time_raw": "1:16.166",
      "source_session": "Q2",
      "perf_pct": 101.601
    },
    {
      "driver_id": 730,
      "team": "",
      "best_time_ms": 75600,
      "best_time_raw": "1:15.600",
      "source_session": "EL3",
      "perf_pct": 100.846
    },
    {
      "driver_id": 732,
      "team": "",
      "best_time_ms": 77562,
      "best_time_raw": "1:17.562",
      "source_session": "Q2",
      "perf_pct": 103.463
    },
    {
      "driver_id": 737,
      "team": "",
      "best_time_ms": 76133,
      "best_time_raw": "1:16.133",
      "source_session": "EL3",
      "perf_pct": 101.557
    },
    {
      "driver_id": 741,
      "team": "",
      "best_time_ms": 78696,
      "best_time_raw": "1:18.696",
      "source_session": "EL3",
      "perf_pct": 104.976
    },
    {
      "driver_id": 747,
      "team": "",
      "best_time_ms": 77908,
      "best_time_raw": "1:17.908",
      "source_session": "EL3",
      "perf_pct": 103.924
    },
    {
      "driver_id": 753,
      "team": "",
      "best_time_ms": 74966,
      "best_time_raw": "1:14.966",
      "source_session": "EL3",
      "perf_pct": 100.0
    },
    {
      "driver_id": 755,
      "team": "",
      "best_time_ms": 75967,
      "best_time_raw": "1:15.967",
      "source_session": "Q2",
      "perf_pct": 101.335
    },
    {
      "driver_id": 765,
      "team": "",
      "best_time_ms": 77445,
      "best_time_raw": "1:17.445",
      "source_session": "Q2",
      "perf_pct": 103.307
    },
    {
      "driver_id": 767,
      "team": "",
      "best_time_ms": 76039,
      "best_time_raw": "1:16.039",
      "source_session": "EL3",
      "perf_pct": 101.431
    },
    {
      "driver_id": 770,
      "team": "",
      "best_time_ms": 75136,
      "best_time_raw": "1:15.136",
      "source_session": "Q2",
      "perf_pct": 100.227
    },
    {
      "driver_id": 771,
      "team": "",
      "best_time_ms": 75533,
      "best_time_raw": "1:15.533",
      "source_session": "Q2",
      "perf_pct": 100.756
    },
    {
      "driver_id": 777,
      "team": "",
      "best_time_ms": 76112,
      "best_time_raw": "1:16.112",
      "source_session": "EL3",
      "perf_pct": 101.529
    },
    {
      "driver_id": 779,
      "team": "",
      "best_time_ms": 77068,
      "best_time_raw": "1:17.068",
      "source_session": "Q2",
      "perf_pct": 102.804
    },
    {
      "driver_id": 780,
      "team": "",
      "best_time_ms": 78514,
      "best_time_raw": "1:18.514",
      "source_session": "Q2",
      "perf_pct": 104.733
    },
    {
      "driver_id": 782,
      "team": "",
      "best_time_ms": 76965,
      "best_time_raw": "1:16.965",
      "source_session": "Q2",
      "perf_pct": 102.667
    },
    {
      "driver_id": 783,
      "team": "",
      "best_time_ms": 79044,
      "best_time_raw": "1:19.044",
      "source_session": "EL3",
      "perf_pct": 105.44
    },
    {
      "driver_id": 750,
      "team": "",
      "best_time_ms": 76990,
      "best_time_raw": "1:16.990",
      "source_session": "Q2",
      "perf_pct": 102.7
    },
    {
      "driver_id": 764,
      "team": "",
      "best_time_ms": 77077,
      "best_time_raw": "1:17.077",
      "source_session": "Q2",
      "perf_pct": 102.816
    }
  ]
}