{
  "race_id": 975,
  "generated_at": "2025-10-21T09:01:55Z",
  "schema": "v3.3",
  "drivers": [
    {
      "driver_id": 767,
      "team": "",
      "best_time_ms": 69593,
      "best_time_raw": "1:09.593",
      "source_session": "Q2",
      "perf_pct": 101.86
    },
    {
      "driver_id": 771,
      "team": "",
      "best_time_ms": 68538,
      "best_time_raw": "1:08.538",
      "source_session": "Q3",
      "perf_pct": 100.316
    },
    {
      "driver_id": 774,
      "team": "",
      "best_time_ms": 69612,
      "best_time_raw": "1:09.612",
      "source_session": "Q2",
      "perf_pct": 101.888
    },
    {
      "driver_id": 809,
      "team": "",
      "best_time_ms": 69202,
      "best_time_raw": "1:09.202",
      "source_session": "EL1",
      "perf_pct": 101.288
    },
    {
      "driver_id": 813,
      "team": "",
      "best_time_ms": 68360,
      "best_time_raw": "1:08.360",
      "source_session": "Q3",
      "perf_pct": 100.056
    },
    {
      "driver_id": 819,
      "team": "",
      "best_time_ms": 69879,
      "best_time_raw": "1:09.879",
      "source_session": "Q2",
      "perf_pct": 102.279
    },
    {
      "driver_id": 824,
      "team": "",
      "best_time_ms": 69703,
      "best_time_raw": "1:09.703",
      "source_session": "Q3",
      "perf_pct": 102.021
    },
    {
      "driver_id": 833,
      "team": "",
      "best_time_ms": 69330,
      "best_time_raw": "1:09.330",
      "source_session": "Q3",
      "perf_pct": 101.475
    },
    {
      "driver_id": 842,
      "team": "",
      "best_time_ms": 68322,
      "best_time_raw": "1:08.322",
      "source_session": "Q3",
      "perf_pct": 100.0
    },
    {
      "driver_id": 848,
      "team": "",
      "best_time_ms": 70875,
      "best_time_raw": "1:10.875",
      "source_session": "Q1",
      "perf_pct": 103.737
    },
    {
      "driver_id": 854,
      "team": "",
      "best_time_ms": 70154,
      "best_time_raw": "1:10.154",
      "source_session": "Q2",
      "perf_pct": 102.681
    },
    {
      "driver_id": 855,
      "team": "",
      "best_time_ms": 69830,
      "best_time_raw": "1:09.830",
      "source_session": "Q2",
      "perf_pct": 102.207
    },
    {
      "driver_id": 863,
      "team": "",
      "best_time_ms": 69768,
      "best_time_raw": "1:09.768",
      "source_session": "Q2",
      "perf_pct": 102.116
    },
    {
      "driver_id": 864,
      "team": "",
      "best_time_ms": 68925,
      "best_time_raw": "1:08.925",
      "source_session": "Q3",
      "perf_pct": 100.883
    },
    {
      "driver_id": 868,
      "team": "",
      "best_time_ms": 71801,
      "best_time_raw": "1:11.802",
      "source_session": "EL1",
      "perf_pct": 105.092
    },
    {
      "driver_id": 869,
      "team": "",
      "best_time_ms": 70116,
      "best_time_raw": "1:10.116",
      "source_session": "Q2",
      "perf_pct": 102.626
    },
    {
      "driver_id": 871,
      "team": "",
      "best_time_ms": 70686,
      "best_time_raw": "1:10.686",
      "source_session": "Q1",
      "perf_pct": 103.46
    },
    {
      "driver_id": 875,
      "team": "",
      "best_time_ms": 71047,
      "best_time_raw": "1:11.047",
      "source_session": "EL1",
      "perf_pct": 103.988
    },
    {
      "driver_id": 876,
      "team": "",
      "best_time_ms": 70632,
      "best_time_raw": "1:10.632",
      "source_session": "EL1",
      "perf_pct": 103.381
    },
    {
      "driver_id": 831,
      "team": "",
      "best_time_ms": 69598,
      "best_time_raw": "1:09.598",
      "source_session": "Q3",
      "perf_pct": 101.868
    },
    {
      "driver_id": 870,
      "team": "",
      "best_time_ms": 70678,
      "best_time_raw": "1:10.678",
      "source_session": "Q1",
      "perf_pct": 103.448
    },
    {
      "driver_id": 873,
      "team": "",
      "best_time_ms": 72417,
      "best_time_raw": "1:12.417",
      "source_session": "EL2",
      "perf_pct": 105.994
    },
    {
      "driver_id": 874,
      "team": "",
      "best_time_ms": 70625,
      "best_time_raw": "1:10.625",
      "source_session": "Q1",
      "perf_pct": 103.371
    }
  ]
}